djangocms_events/__about__.py
djangocms_events/__init__.py
djangocms_events/admin.py
djangocms_events/apps.py
djangocms_events/cms_apps.py
djangocms_events/cms_plugins.py
djangocms_events/models.py
djangocms_events/sitemaps.py
djangocms_events/tests.py
djangocms_events/urls.py
djangocms_events/views.py
djangocms_events/migrations/0001_initial.py
djangocms_events/migrations/0002_calendar_default_picture.py
djangocms_events/migrations/0003_alter_calendarplugin_cmsplugin_ptr_and_more.py
djangocms_events/migrations/0004_event_duration.py
djangocms_events/migrations/__init__.py
djangocms_events/static/djangocms_events/semantic.min.js
djangocms_events/static/djangocms_events/webpack/1551f4f60c37af51121f.woff2
djangocms_events/static/djangocms_events/webpack/2285773e6b4b172f07d9.woff
djangocms_events/static/djangocms_events/webpack/2e72ab08f6b108d7eef4.woff
djangocms_events/static/djangocms_events/webpack/2fee7146711cc5c3dd41.woff
djangocms_events/static/djangocms_events/webpack/330c031b5bb2b88046da.woff2
djangocms_events/static/djangocms_events/webpack/43bc627160e4b7a28fbc.woff2
djangocms_events/static/djangocms_events/webpack/497f04acb55a3d00dfa3.woff
djangocms_events/static/djangocms_events/webpack/4a38ade2ce0988376595.woff
djangocms_events/static/djangocms_events/webpack/710a16565cff7fb7bf78.woff2
djangocms_events/static/djangocms_events/webpack/720116e2e1990835048b.woff
djangocms_events/static/djangocms_events/webpack/7a3337626410ca2f4071.woff2
djangocms_events/static/djangocms_events/webpack/8525916133d63443ee21.woff
djangocms_events/static/djangocms_events/webpack/978bab8c991c4aab7d12.woff2
djangocms_events/static/djangocms_events/webpack/9bcbc975bb95fcc7bdbb.woff
djangocms_events/static/djangocms_events/webpack/b0a598e91a6ca2310dc9.woff2
djangocms_events/static/djangocms_events/webpack/bb58e57c48a3e911f15f.woff
djangocms_events/static/djangocms_events/webpack/bb932b70aeb593860dfe.woff2
djangocms_events/static/djangocms_events/webpack/calendar.bundle.js
djangocms_events-0.1.8.dist-info/METADATA
djangocms_events-0.1.8.dist-info/WHEEL
djangocms_events-0.1.8.dist-info/licenses/LICENSE.txt
djangocms_events-0.1.8.dist-info/RECORD
