Metadata-Version: 2.1
Name: djangocms-events
Version: 0.1.8
Summary: Events list and calendar for django CMS
Project-URL: Homepage, https://github.com/MacLake/djangocms-events
Project-URL: repository, https://github.com/MacLake/djangocms-events.git
Author-email: Jens-Erik Weber <web@passiv.de>
License: MIT License
License-File: LICENSE.txt
Classifier: Environment :: Web Environment
Classifier: Framework :: Django
Classifier: Framework :: Django :: 3.2
Classifier: Framework :: Django :: 4.0
Classifier: Framework :: Django :: 4.1
Classifier: Framework :: Django :: 4.2
Classifier: Intended Audience :: Developers
Classifier: License :: OSI Approved :: MIT License
Classifier: Operating System :: OS Independent
Classifier: Programming Language :: Python
Classifier: Programming Language :: Python :: 3
Classifier: Programming Language :: Python :: 3 :: Only
Classifier: Programming Language :: Python :: 3.9
Classifier: Programming Language :: Python :: 3.10
Classifier: Topic :: Internet :: WWW/HTTP
Classifier: Topic :: Internet :: WWW/HTTP :: Dynamic Content
Requires-Python: >=3.9
Requires-Dist: arrow>=1.2
Requires-Dist: django-cms>=3.11
Requires-Dist: django-filer>=2.2
Requires-Dist: django-quill-editor>=0.1
Requires-Dist: django>=3.2
Requires-Dist: easy-thumbnails>=2.8
Requires-Dist: ics>=0.7
Requires-Dist: requests>=2.28
